emoji_chengyu/__init__.py
emoji_chengyu/data.py
emoji_chengyu/main.py
emoji_chengyu/puzzle.py
emoji_chengyu/data/chengyu.count.json
emoji_chengyu/data/chengyu.json
emoji_chengyu/data/emoji.cn.json
emoji_chengyu-0.0.6.dist-info/METADATA
emoji_chengyu-0.0.6.dist-info/WHEEL
emoji_chengyu-0.0.6.dist-info/entry_points.txt
emoji_chengyu-0.0.6.dist-info/licenses/LICENSE
emoji_chengyu-0.0.6.dist-info/RECORD
