Metadata-Version: 2.1
Name: emoji-chengyu
Version: 0.0.6
Summary: 把成语转成 emoji 来猜谜的小玩具, 可以用于中秋, 元宵猜灯谜
Project-URL: Homepage, https://github.com/alingse/emoji-chengyu
Author-email: alingse <alingse@foxmail.com>
License-Expression: MIT
License-File: LICENSE
Keywords: chengyu,emoji,emoji-chengyu,成语
Classifier: Operating System :: OS Independent
Classifier: Programming Language :: Python :: 3
Requires-Dist: click
